GridPythonModule/GridPyM.py
GridPythonModule/__init__.py
GridPythonModule-0.1.2.dist-info/LICENSE
GridPythonModule-0.1.2.dist-info/METADATA
GridPythonModule-0.1.2.dist-info/WHEEL
GridPythonModule-0.1.2.dist-info/top_level.txt
GridPythonModule-0.1.2.dist-info/RECORD
